ryzetello/__init__.py
ryzetello/commands.py
ryzetello/missionpads.py
ryzetello-1.6.dist-info/LICENSE
ryzetello-1.6.dist-info/METADATA
ryzetello-1.6.dist-info/WHEEL
ryzetello-1.6.dist-info/top_level.txt
ryzetello-1.6.dist-info/RECORD
